appie
