Metadata-Version: 1.0
Name: appie
Version: 0.0.4
Summary: A Python library for the (hidden) AH rest interface
Home-page: https://github.com/svdgraaf/appie
Author: Sander van de Graaf
Author-email: mail@svdgraaf.nl
License:                     GNU GENERAL PUBLIC LICENSE
